dsbase/__init__.py
dsbase/animation.py
dsbase/argparser.py
dsbase/common/__init__.py
dsbase/common/singleton.py
dsbase/configs/__init__.py
dsbase/configs/code_configs.py
dsbase/configs/configs/mypy.ini
dsbase/configs/configs/ruff.toml
dsbase/db/__init__.py
dsbase/db/db_common.py
dsbase/db/mysql_helper.py
dsbase/db/sqlite_helper.py
dsbase/diff.py
dsbase/env/README.md
dsbase/env/__init__.py
dsbase/env/env.py
dsbase/env/env_var.py
dsbase/files/__init__.py
dsbase/files/compare.py
dsbase/files/copy.py
dsbase/files/delete.py
dsbase/files/file_manager.py
dsbase/files/list.py
dsbase/log/__init__.py
dsbase/log/local_logger.py
dsbase/log/log_formatters.py
dsbase/log/log_metadata.py
dsbase/log/time_aware_logger.py
dsbase/macos.py
dsbase/media/__init__.py
dsbase/media/ffmpeg.py
dsbase/media/media.py
dsbase/media/media_manager.py
dsbase/media/video_helper.py
dsbase/notifiers/README.md
dsbase/notifiers/__init__.py
dsbase/notifiers/send_mail.py
dsbase/notifiers/send_telegram.py
dsbase/notifiers/telegram_api.py
dsbase/paths.py
dsbase/progress.py
dsbase/shell.py
dsbase/text.py
dsbase/time/__init__.py
dsbase/time/time.py
dsbase/tools/__init__.py
dsbase/tools/decorators.py
dsbase/tools/errors.py
dsbase/types.py
dsbase-1.11.0.dist-info/LICENSE
dsbase-1.11.0.dist-info/METADATA
dsbase-1.11.0.dist-info/WHEEL
dsbase-1.11.0.dist-info/entry_points.txt
dsbase-1.11.0.dist-info/RECORD
