Metadata-Version: 2.3
Name: dsbase
Version: 1.11.0
Summary: Personal Python utility library
License: GPL-3.0-or-later
Author: Danny Stewart
Author-email: danny@stewart.cc
Requires-Python: >=3.12
Classifier: License :: OSI Approved :: GNU General Public License v3 or later (GPLv3+)
Classifier: Programming Language :: Python :: 3
Classifier: Programming Language :: Python :: 3.12
Classifier: Programming Language :: Python :: 3.13
Provides-Extra: dev
Requires-Dist: halo (>=0.0.31)
Requires-Dist: mypy (>=1.15.0) ; extra == "dev"
Requires-Dist: natsort (>=8.4.0)
Requires-Dist: platformdirs (>=4.3.6)
Requires-Dist: pygments (>=2.19.1)
Requires-Dist: python-dateutil (>=2.9.0.post0)
Requires-Dist: python-dotenv (>=1.0.1)
Requires-Dist: requests (>=2.32.3)
Requires-Dist: ruff (>=0.10.0) ; extra == "dev"
Requires-Dist: send2trash (>=1.8.3)
Requires-Dist: termcolor (>=2.5.0)
Requires-Dist: types-requests (>=2.32.0.20250306)
Requires-Dist: types-send2trash (>=1.8.2.7)
Requires-Dist: tzdata (>=2025.1)
